messenger2/__init__.py
messenger2/client_start.py
messenger2/config.py
messenger2/server.ini
messenger2/client/__init__.py
messenger2/client/transport.py
messenger2/client/gui/__init__.py
messenger2/client/gui/add_contact.py
messenger2/client/gui/alert_window.py
messenger2/client/gui/client_window.py
messenger2/client/gui/del_contact.py
messenger2/client/gui/open_dialog.py
messenger2/client/gui/welcome.py
messenger2/client/gui/ui/__init__.py
messenger2/client/gui/ui/add_client.ui
messenger2/client/gui/ui/client.ui
messenger2/client/gui/ui/del_client.ui
messenger2/client/gui/ui/open_dialog.ui
messenger2/client/gui/ui/welcome.ui
messenger2/common/__init__.py
messenger2/common/decorators.py
messenger2/common/descriptors.py
messenger2/common/metaclasses.py
messenger2/common/security/__init__.py
messenger2/common/security/decript_data.py
messenger2/common/security/encript_data.py
messenger2/common/security/hash_password.py
messenger2/common/security/keys.py
messenger2/databases/__init__.py
messenger2/databases/database.py
messenger2/logs/__init__.py
messenger2/logs/client_logs/__init__.py
messenger2/logs/log_configs/__init__.py
messenger2/logs/log_configs/client_log_config.py
messenger2/logs/log_configs/server_log_config.py
messenger2/logs/server_logs/__init__.py
messenger2/protocols/BaseProtocol.py
messenger2/protocols/JIM.py
messenger2/protocols/__init__.py
python_messenger_client-0.0.5.dist-info/METADATA
python_messenger_client-0.0.5.dist-info/WHEEL
python_messenger_client-0.0.5.dist-info/top_level.txt
python_messenger_client-0.0.5.dist-info/RECORD
