Metadata-Version: 2.1
Name: python-messenger-client
Version: 0.0.5
Summary: Messenger Client
Home-page: UNKNOWN
Author: Sergey Kurskiy
Author-email: kurskiisergey@mail.ru
License: UNKNOWN
Platform: UNKNOWN
Requires-Dist: PySide2
Requires-Dist: sqlalchemy
Requires-Dist: pycryptodome
Requires-Dist: pycryptodomex
